{
	"_id": "postcss-google-font",
	"_rev": "7-5ecc7800c78c612046fda2dafa418c5e",
	"name": "postcss-google-font",
	"description": "PostCSS plugin for import Google fonts",
	"dist-tags": {
		"latest": "1.1.0"
	},
	"versions": {
		"0.1.0": {
			"name": "postcss-google-font",
			"version": "0.1.0",
			"description": "PostCSS plugin for import Google fonts",
			"main": "./lib/index.js",
			"keywords": [
				"postcss",
				"css",
				"postcss-plugin",
				"google",
				"fonts"
			],
			"author": {
				"name": "Yordis Prieto",
				"email": "yordis.prieto@gmail.com"
			},
			"license": "MIT",
			"repository": {
				"type": "git",
				"url": "git+https://github.com/yordis/postcss-google-font.git"
			},
			"bugs": {
				"url": "https://github.com/yordis/postcss-google-font/issues"
			},
			"homepage": "https://github.com/yordis/postcss-google-font",
			"dependencies": {
				"postcss": "^5.0.13"
			},
			"devDependencies": {
				"ava": "^0.10.0"
			},
			"scripts": {
				"test": "ava"
			},
			"gitHead": "d964ab2427731d1f9caf5cfdf8acfe715dbd820c",
			"_id": "postcss-google-font@0.1.0",
			"_shasum": "b836339f7e9eef0b1aa46d7ad7d368a04900b5a4",
			"_from": ".",
			"_npmVersion": "3.3.12",
			"_nodeVersion": "5.3.0",
			"_npmUser": {
				"name": "ubi",
				"email": "yordis.prieto@gmail.com"
			},
			"dist": {
				"shasum": "b836339f7e9eef0b1aa46d7ad7d368a04900b5a4",
				"tarball": "https://registry.npmjs.org/postcss-google-font/-/postcss-google-font-0.1.0.tgz",
				"integrity": "sha512-q4Muj7yVxqX1vQI6eZ4EtToVWDhy9Q9MbIWiy0HHF2+ynsEmmYf9VPAYOIXsldvT1T/pBzmG1z4QzB5L0xR5iw==",
				"signatures": [
					{
						"keyid": "SHA256:jl3bwswu80PjjokCgh0o2w5c2U4LhQAE57gj9cz1kzA",
						"sig": "MEUCIQDWGVGIOzv3gm8+MphTHNKgCNYB6AAxtBb04rhiW1DVnwIgfs2JMvto/RXBBVwDl649Y3hw2UQ/DGrirNMpBE6I0xc="
					}
				]
			},
			"maintainers": [
				{
					"name": "ubi",
					"email": "yordis.prieto@gmail.com"
				}
			],
			"directories": {}
		},
		"0.1.1": {
			"name": "postcss-google-font",
			"version": "0.1.1",
			"description": "PostCSS plugin for import Google fonts",
			"main": "./lib/index.js",
			"keywords": [
				"postcss",
				"css",
				"postcss-plugin",
				"google",
				"fonts"
			],
			"author": {
				"name": "Yordis Prieto",
				"email": "yordis.prieto@gmail.com"
			},
			"license": "MIT",
			"repository": {
				"type": "git",
				"url": "git+https://github.com/yordis/postcss-google-font.git"
			},
			"bugs": {
				"url": "https://github.com/yordis/postcss-google-font/issues"
			},
			"homepage": "https://github.com/yordis/postcss-google-font",
			"dependencies": {
				"postcss": "^5.0.13"
			},
			"devDependencies": {
				"ava": "^0.10.0"
			},
			"scripts": {
				"test": "ava"
			},
			"gitHead": "f4c4ab9aa732b3fa231ee5ed8b97fc51d80ad493",
			"_id": "postcss-google-font@0.1.1",
			"_shasum": "b57c7fbfff276d9d7d2397bac2e0cf61ebc797cf",
			"_from": ".",
			"_npmVersion": "3.3.12",
			"_nodeVersion": "5.3.0",
			"_npmUser": {
				"name": "ubi",
				"email": "yordis.prieto@gmail.com"
			},
			"dist": {
				"shasum": "b57c7fbfff276d9d7d2397bac2e0cf61ebc797cf",
				"tarball": "https://registry.npmjs.org/postcss-google-font/-/postcss-google-font-0.1.1.tgz",
				"integrity": "sha512-F0N6f7juuPhxBdqXS42k41Bz+u4MLLTEbMbBKQ7xg5OGhw9tBTA9na7VDjlaoQ6U3lk+vpo+509tEBF6d3nIeA==",
				"signatures": [
					{
						"keyid": "SHA256:jl3bwswu80PjjokCgh0o2w5c2U4LhQAE57gj9cz1kzA",
						"sig": "MEQCIBJA1TU9ZxBd1pMb+QDoEMmDsHhzkVHUSy0NFxw6qb3LAiBJrnW5GAOPZq5wdk+WTdS759lFXsEaU9lH68ciU/zceg=="
					}
				]
			},
			"maintainers": [
				{
					"name": "ubi",
					"email": "yordis.prieto@gmail.com"
				}
			],
			"directories": {}
		},
		"1.0.0": {
			"name": "postcss-google-font",
			"version": "1.0.0",
			"description": "PostCSS plugin for import Google fonts",
			"main": "./lib/index.js",
			"keywords": [
				"postcss",
				"css",
				"postcss-plugin",
				"google",
				"fonts"
			],
			"author": {
				"name": "Yordis Prieto",
				"email": "yordis.prieto@gmail.com"
			},
			"license": "MIT",
			"repository": {
				"type": "git",
				"url": "https://github.com/yordis/postcss-google-font.git"
			},
			"bugs": {
				"url": "https://github.com/yordis/postcss-google-font/issues"
			},
			"homepage": "https://github.com/yordis/postcss-google-font",
			"dependencies": {
				"postcss": "^7.0.32"
			},
			"devDependencies": {
				"@straw-hat/prettier-config": "1.0.1",
				"jest": "26.1.0"
			},
			"scripts": {
				"test": "jest"
			},
			"licenseText": "The MIT License (MIT)\n\nCopyright 2015 Yordis Prieto <yordis.prieto@gmail.com>\n\nPermission is hereby granted, free of charge, to any person obtaining a copy of\nthis software and associated documentation files (the \"Software\"), to deal in\nthe Software without restriction, including without limitation the rights to\nuse, copy, modify, merge, publish, distribute, sublicense, and/or sell copies of\nthe Software, and to permit persons to whom the Software is furnished to do so,\nsubject to the following conditions:\n\nThe above copyright notice and this permission notice shall be included in all\ncopies or substantial portions of the Software.\n\nTHE SOFTWARE IS PROVIDED \"AS IS\", WITHOUT WARRANTY OF ANY KIND, EXPRESS OR\nIMPLIED, INCLUDING BUT NOT LIMITED TO THE WARRANTIES OF MERCHANTABILITY, FITNESS\nFOR A PARTICULAR PURPOSE AND NONINFRINGEMENT. IN NO EVENT SHALL THE AUTHORS OR\nCOPYRIGHT HOLDERS BE LIABLE FOR ANY CLAIM, DAMAGES OR OTHER LIABILITY, WHETHER\nIN AN ACTION OF CONTRACT, TORT OR OTHERWISE, ARISING FROM, OUT OF OR IN\nCONNECTION WITH THE SOFTWARE OR THE USE OR OTHER DEALINGS IN THE SOFTWARE.\n",
			"_id": "postcss-google-font@1.0.0",
			"dist": {
				"shasum": "1b46ec7601173571b8127a8971890f7a863b63bf",
				"integrity": "sha512-lEFBXgfSqqsrqhBCtQF7ye5wJcoA6a7MRKLapcsRxzqCS7JGnM/Y2uEG6o8hg3a9eSmDP98hsRZyAmWHQJJLiw==",
				"tarball": "https://registry.npmjs.org/postcss-google-font/-/postcss-google-font-1.0.0.tgz",
				"fileCount": 10,
				"unpackedSize": 6605,
				"npm-signature": "-----BEGIN PGP SIGNATURE-----\r\nVersion: OpenPGP.js v3.0.4\r\nComment: https://openpgpjs.org\r\n\r\nwsFcBAEBCAAQBQJfBAWBCRA9TVsSAnZWagAA9zQP+wQir9R6Oa1hu3HmHEur\n3lwKZQW2rLsvK8ODEK9lylZFUR7L1DH6r2ZeQRaz/ZcT0rBW6gh17Z5ai0dQ\nNky8bXHg2cxWyHaK0pyqxii7NChNEu35FUNAozdPHNvvWz7U+ZETiCZAKPqu\nB2KvXKzbJGjlRS2Jheps0Bp5PpWw46X5mUeNaR6dAMaocXAi5SVA/2izJsFZ\n3HQmppKlaG8KWnUMwrDt1G5dGmIUiG//tixpFg9FyqNqKrDRachscD6uExBV\nDCar4KZ8v1GyBdpLif7KhBvbHvCH1MJ/fjmOmhstpnl3cAQNaFAZ6QZHL8YB\nGxnQYUNmrskAgdlykclxyf7rpyuiLzCEstjLP6pXrtPcx7r3nJs82BPMZcOT\naFf2PO/vygC69MQYz1YOpuA83GvY3c8jEAsQO5crr/wD3JVxsdZH0S7a/gzK\n1NHyVE68Nqq28GTjL5s2mzk42hlEHTLQfNO+j35qVJ/iNNK9ZNThfw9RYCxp\n/UEF1cMCF0SAr/Xba4ahWYJDXkbAyavH/4QC2Z0KKRCNXz8Y0wqGBFKs6gpo\nqZTOufjzDRwLczkoZi4cfaXB1JXnLP9CQsGV0JctDRXNDMcRXKaahjMkm0UI\nT2J7WZOw6+N3yvsuAZlfd/vWhJwCYgps6fWBQ7WW3MFJXc5v+SgpY2UOlM0H\nQpIR\r\n=NE3r\r\n-----END PGP SIGNATURE-----\r\n",
				"signatures": [
					{
						"keyid": "SHA256:jl3bwswu80PjjokCgh0o2w5c2U4LhQAE57gj9cz1kzA",
						"sig": "MEYCIQDwB8w+bOUX3a63evCzxeGqCUooatIGgFWXsrQNkuBy+gIhAK9tArh73Z2B1Rg8B0KjFVnL+gMwvo52jTfD2gVIIBDs"
					}
				]
			},
			"maintainers": [
				{
					"name": "ubi",
					"email": "yordis.prieto@gmail.com"
				}
			],
			"_npmUser": {
				"name": "ubi",
				"email": "yordis.prieto@gmail.com"
			},
			"directories": {},
			"_npmOperationalInternal": {
				"host": "s3://npm-registry-packages",
				"tmp": "tmp/postcss-google-font_1.0.0_1594099073386_0.573223814809781"
			},
			"_hasShrinkwrap": false
		},
		"1.1.0": {
			"name": "postcss-google-font",
			"version": "1.1.0",
			"description": "PostCSS plugin for import Google fonts",
			"main": "./lib/index.js",
			"keywords": [
				"postcss",
				"css",
				"postcss-plugin",
				"google",
				"fonts"
			],
			"author": {
				"name": "Yordis Prieto",
				"email": "yordis.prieto@gmail.com"
			},
			"license": "MIT",
			"repository": {
				"type": "git",
				"url": "https://github.com/yordis/postcss-google-font.git"
			},
			"bugs": {
				"url": "https://github.com/yordis/postcss-google-font/issues"
			},
			"homepage": "https://github.com/yordis/postcss-google-font",
			"dependencies": {
				"postcss": "^7.0.32"
			},
			"devDependencies": {
				"@straw-hat/prettier-config": "1.0.1",
				"jest": "26.1.0"
			},
			"scripts": {
				"test": "jest"
			},
			"licenseText": "The MIT License (MIT)\n\nCopyright 2015 Yordis Prieto <yordis.prieto@gmail.com>\n\nPermission is hereby granted, free of charge, to any person obtaining a copy of\nthis software and associated documentation files (the \"Software\"), to deal in\nthe Software without restriction, including without limitation the rights to\nuse, copy, modify, merge, publish, distribute, sublicense, and/or sell copies of\nthe Software, and to permit persons to whom the Software is furnished to do so,\nsubject to the following conditions:\n\nThe above copyright notice and this permission notice shall be included in all\ncopies or substantial portions of the Software.\n\nTHE SOFTWARE IS PROVIDED \"AS IS\", WITHOUT WARRANTY OF ANY KIND, EXPRESS OR\nIMPLIED, INCLUDING BUT NOT LIMITED TO THE WARRANTIES OF MERCHANTABILITY, FITNESS\nFOR A PARTICULAR PURPOSE AND NONINFRINGEMENT. IN NO EVENT SHALL THE AUTHORS OR\nCOPYRIGHT HOLDERS BE LIABLE FOR ANY CLAIM, DAMAGES OR OTHER LIABILITY, WHETHER\nIN AN ACTION OF CONTRACT, TORT OR OTHERWISE, ARISING FROM, OUT OF OR IN\nCONNECTION WITH THE SOFTWARE OR THE USE OR OTHER DEALINGS IN THE SOFTWARE.\n",
			"_id": "postcss-google-font@1.1.0",
			"dist": {
				"shasum": "859487baf8cbe95008c528f3e3f3b519d5d7afd9",
				"integrity": "sha512-RRy3En+APsASoQVia4JtRnYlvllau14Gla6oovynHyPQvgLjM5ziGnys55AaUvZ56hLZfyzwGsI1W0/Osjg93g==",
				"tarball": "https://registry.npmjs.org/postcss-google-font/-/postcss-google-font-1.1.0.tgz",
				"fileCount": 10,
				"unpackedSize": 6934,
				"npm-signature": "-----BEGIN PGP SIGNATURE-----\r\nVersion: OpenPGP.js v3.0.13\r\nComment: https://openpgpjs.org\r\n\r\nwsFcBAEBCAAQBQJfyyjSCRA9TVsSAnZWagAAYyEP/jJTLNmdXKuVI1oCIYNg\nSeYko5IgHYxk30s/KSmRhM9DLAG46ghtqrUdZFrNDOq1KKAhfn0PN4h8zD6w\nq04p7fKK5VZa4Qv5YCNxf2NaVqITbLL4SWobhNZKaZsmpLSvxDSrgHC/hjmV\n9rOek0J9UkTJNOC46cpn8wzmXzicbljm0lj5gAfW3n1Gx3mhky9hbMS4WhM0\nJHc+GkZr9NkuqUPmfrWY2yfa5AQoT4v2wuZTBcZavPPqi89bJ2J3t4DadlNF\nChyUyy4ClkW6OVNjjKmxuGCriSB/6Y8Uwdi+sljTM8ITsiTjDKGjHMknJFhN\np9YOyP9WZT0/36JGY2elcUXdAMfX5fhI8kWL5MmXx6tgx9oh+zcPjTZCxCbu\nbyxXnbso61XRDTgguofTsDhwoUkcNi7csttKbrq9m5hhHoStF0awWXyanXZZ\n7gnvG3vWIS+rWsQmBzuofGtnHkCAksYtIetNmTsu3tBfJXyB4Av2OvMsVvpV\nGarDcCllWTVloQLPPmilnJqr4gLjmuQVzuSuq+GoPN0ESJ2lBowd94tZQH1+\noJy5eicp7+4HOYV9j5RGdxZhLr7FRsxW3f94oaCr+xfMC/THneDK/A6/5fsm\nUGeu0Afq9M0BgBmH1yZyImgVBRCxIMlPoQdi3wWODUEtt7m+JxKKbUcZgRzj\n3cXo\r\n=L5+H\r\n-----END PGP SIGNATURE-----\r\n",
				"signatures": [
					{
						"keyid": "SHA256:jl3bwswu80PjjokCgh0o2w5c2U4LhQAE57gj9cz1kzA",
						"sig": "MEUCIHUgZc7bBj/fyHuvSR72ML5LVyP2qR5bu8DbrZNY40L8AiEAlKm44+S/r8RrRKx8zMassiOcDKrYwinC5feGqvGPzT8="
					}
				]
			},
			"_npmUser": {
				"name": "ubi",
				"email": "yordis.prieto@gmail.com"
			},
			"directories": {},
			"maintainers": [
				{
					"name": "ubi",
					"email": "yordis.prieto@gmail.com"
				}
			],
			"_npmOperationalInternal": {
				"host": "s3://npm-registry-packages",
				"tmp": "tmp/postcss-google-font_1.1.0_1607149777760_0.8707169722030113"
			},
			"_hasShrinkwrap": false
		}
	},
	"readme": "# PostCSS Google Font\n\n[PostCSS] plugin for import Google fonts.\n\n**Syntax:** `@google-font font-family styles [args]`\n\n- **font-family**: The name of the font. **Compound family names** should\n  be wrapped out inside quotes or double quotes\n- **styles**: The styles of the font. Use the comma for separated multiples\n  styles: `400,500,700italic`\n- **args** (optional): The dislpay and subset of the font:\n  `display=swap,subset=latin|latin-ext`\n\n```css\n@google-font Lato 400 subset=latin;\n@google-font Lato 400 display=swap,subset=latin|latin-ext;\n```\n\n```css\n@import url(https://fonts.googleapis.com/css?family=Lato:400?subset=latin);\n@import url(https://fonts.googleapis.com/css?family=Lato:400?display=swap&subset=latin,latin-ext);\n```\n\n## Usage\n\n```js\npostcss([ require('postcss-google-font') ])\n```\n\nSee [PostCSS] docs for examples for your environment.\n\n[PostCSS]: https://github.com/postcss/postcss\n[ci-img]:  https://travis-ci.org/yordis/postcss-google-font.svg\n[ci]:      https://travis-ci.org/yordis/postcss-google-font\n",
	"maintainers": [
		{
			"name": "ubi",
			"email": "yordis.prieto@gmail.com"
		}
	],
	"time": {
		"modified": "2022-06-24T10:04:24.302Z",
		"created": "2016-01-19T13:03:06.969Z",
		"0.1.0": "2016-01-19T13:03:06.969Z",
		"0.1.1": "2016-01-19T13:04:43.994Z",
		"1.0.0": "2020-07-07T05:17:53.487Z",
		"1.1.0": "2020-12-05T06:29:37.985Z"
	},
	"homepage": "https://github.com/yordis/postcss-google-font",
	"keywords": [
		"postcss",
		"css",
		"postcss-plugin",
		"google",
		"fonts"
	],
	"repository": {
		"type": "git",
		"url": "https://github.com/yordis/postcss-google-font.git"
	},
	"author": {
		"name": "Yordis Prieto",
		"email": "yordis.prieto@gmail.com"
	},
	"bugs": {
		"url": "https://github.com/yordis/postcss-google-font/issues"
	},
	"license": "MIT",
	"readmeFilename": "README.md",
	"_downloads": 231
}