{
	"_id": "postcss-stats",
	"_rev": "10-8a92be54a004e16a1c5612b02d05ab99",
	"name": "postcss-stats",
	"dist-tags": {
		"beta": "0.0.0",
		"latest": "1.1.0"
	},
	"versions": {
		"0.0.0": {
			"name": "postcss-stats",
			"version": "0.0.0",
			"description": "",
			"main": "index.js",
			"scripts": {
				"test": "echo \"Error: no test specified\" && exit 1"
			},
			"repository": {
				"type": "git",
				"url": "git+https://github.com/buz-zard/postcss-stats.git"
			},
			"keywords": [],
			"author": {
				"name": "Karolis Šarapnickis"
			},
			"license": "MIT",
			"bugs": {
				"url": "https://github.com/buz-zard/postcss-stats/issues"
			},
			"homepage": "https://github.com/buz-zard/postcss-stats#readme",
			"gitHead": "280c8308718e0daca8c5d104232a112be9c2a86d",
			"_id": "postcss-stats@0.0.0",
			"_npmVersion": "5.6.0",
			"_nodeVersion": "8.11.1",
			"_npmUser": {
				"name": "karolis.sarapnickis",
				"email": "pastas.k@gmail.com"
			},
			"dist": {
				"integrity": "sha512-gLwajVHH2EcJIaF935p4jy1THCSc5TG0b4oIhjM2BmWDheRxofcRCqUTCdRcd97zGMG+M45bO40Ch0Td8HYltw==",
				"shasum": "dac2f94714160b7cd471b3558ead7d07fc9d417d",
				"tarball": "https://registry.npmjs.org/postcss-stats/-/postcss-stats-0.0.0.tgz",
				"fileCount": 4,
				"unpackedSize": 1589,
				"npm-signature": "-----BEGIN PGP SIGNATURE-----\r\nVersion: OpenPGP.js v3.0.4\r\nComment: https://openpgpjs.org\r\n\r\nwsFcBAEBCAAQBQJb6Q6TCRA9TVsSAnZWagAAsSMQAJJJp9DtxXXJIQL/60Xo\nA9YE9/43KHJ2ZPubiS6E56ak1IId6yNgP9YCE1R1OY8rUh6H0vpDnPNriqIj\nSKo7V2xj4jzV/ptuOFtFmoeqyDpJXbjNqyzNvH6DN//eVw972yDWCVm7J9UH\n/mHXA2HPYlTzq6SBHrE2hYifNKTJShD8JO21IitmV2vekbddMVBkxdF4bEen\nNIVEBW21I2n+6MBjLXxk8FZWke0Yi8VCfynhMDJrD1MtK+e6QNZrVdT4GA9h\nm7bkkHm9g2f+H0xRA6s/Bn3P1X8VXdmKS20HAziNE3I7y4J6yvBYn2Gj0g6A\n76/DlLdy4nKL4Z6uLIr89h+knZOtLfB3aZtVtMQGdQJV518RC313u85yVO/M\n8QPNkjN5DxlPS8GZ/CljMxpsilFc1XsWW0TMUQBc/fcOgL7N/W7w4NOffpLJ\nuM5pRoMjkpg0MVY5rR4biZqL9imyN/Fwos0HkvrFpcp5gqnRWBPhPQQl2o0l\nvLpQfgJvxDHVuJMQgEstXKht7KdAW7mUe2fxWK7BQ55V3U+HwWggRM/LC8tz\nzxR7o8FpMToYbpStkrfXPjRgJz/W7ZYtEmtjBT5tASn2IEAG5qW73O4Bep4i\ntJKDIVqWFCi6C5S3BekGq6MH7t2EUvoyOLtNFUfivXh6b4bMEmaFHoUr2eSx\ng5u+\r\n=xF86\r\n-----END PGP SIGNATURE-----\r\n",
				"signatures": [
					{
						"keyid": "SHA256:jl3bwswu80PjjokCgh0o2w5c2U4LhQAE57gj9cz1kzA",
						"sig": "MEYCIQCvJlDb73Eg7rWoelpvHY7PGcDbt5pguuUOAn0kZIIviQIhANSwinfJFmsvuvXtg/5DvpcBzfdUjvYtKRPmwDhvVkXj"
					}
				]
			},
			"maintainers": [
				{
					"name": "karolis.sarapnickis",
					"email": "pastas.k@gmail.com"
				}
			],
			"directories": {},
			"_npmOperationalInternal": {
				"host": "s3://npm-registry-packages",
				"tmp": "tmp/postcss-stats_0.0.0_1542000274918_0.8030588444616231"
			},
			"_hasShrinkwrap": false,
			"deprecated": "Not"
		},
		"1.0.0": {
			"name": "postcss-stats",
			"version": "1.0.0",
			"description": "A PostCSS plugin to display stats",
			"keywords": [
				"css",
				"postcss",
				"postcss-plugin",
				"stats"
			],
			"homepage": "https://github.com/buz-zard/postcss-stats#readme",
			"bugs": {
				"url": "https://github.com/buz-zard/postcss-stats/issues"
			},
			"repository": {
				"type": "git",
				"url": "git+https://github.com/buz-zard/postcss-stats.git"
			},
			"license": "MIT",
			"author": {
				"name": "Karolis Šarapnickis"
			},
			"main": "lib/index.js",
			"scripts": {
				"build": "babel src --out-dir lib --source-maps",
				"clean": "rimraf lib",
				"develop": "npm run build -- --watch",
				"format": "prettier --write '**/*.*' && sort-package-json",
				"lint": "run-p lint:*",
				"lint:js": "eslint .",
				"lint:md": "markdownlint *.md -i node_modules",
				"qa": "run-p lint test",
				"semantic-release": "semantic-release",
				"test": "jest",
				"travis-deploy-once": "travis-deploy-once"
			},
			"husky": {
				"hooks": {
					"pre-commit": "lint-staged",
					"pre-push": "npm run qa"
				}
			},
			"config": {
				"commitizen": {
					"path": "cz-conventional-changelog"
				}
			},
			"jest": {
				"testRegex": "src/.+\\.test\\.js$"
			},
			"dependencies": {
				"brotli-size": "0.0.3",
				"chalk": "^2.4.1",
				"cli-table": "^0.3.1",
				"cssstats": "^3.2.0",
				"gzip-size": "^5.0.0",
				"pretty-bytes": "^5.1.0"
			},
			"devDependencies": {
				"@babel/cli": "^7.1.5",
				"@babel/core": "^7.1.5",
				"@babel/preset-env": "^7.1.5",
				"@k.sh/eslint-config": "^1.5.0",
				"babel-core": "^7.0.0-bridge.0",
				"babel-eslint": "^10.0.1",
				"babel-jest": "^23.6.0",
				"cz-conventional-changelog": "^2.1.0",
				"husky": "^1.1.3",
				"jest": "^23.6.0",
				"lint-staged": "^8.0.4",
				"markdownlint-cli": "^0.13.0",
				"npm-run-all": "^4.1.3",
				"postcss": "^7.0.6",
				"postcss-replace": "^1.0.3",
				"pretty-quick": "^1.8.0",
				"rimraf": "^2.6.2",
				"semantic-release": "^15.12.0",
				"sort-package-json": "^1.16.0",
				"travis-deploy-once": "^5.0.9"
			},
			"peerDependencies": {
				"postcss": ">= 7.0.0"
			},
			"lint-staged": {
				"*.js": [
					"eslint --fix",
					"git add"
				],
				"*.{md,json}": [
					"pretty-quick --staged"
				]
			},
			"gitHead": "b99b909f85b63f9d928e45a12dbdffbbcd31e0ea",
			"_id": "postcss-stats@1.0.0",
			"_npmVersion": "6.4.1",
			"_nodeVersion": "10.13.0",
			"_npmUser": {
				"name": "karolis.sarapnickis",
				"email": "pastas.k@gmail.com"
			},
			"dist": {
				"integrity": "sha512-/10rmRTF7Dlq5HEZMzM0Pw+y8PQhaxTwU56MZJpL0uWI8+kSDj2PbfbxPNBLrhA1Joenjl5v3r/u27RSUHFoYw==",
				"shasum": "abef2e453c0549b6935c9cdc56b11a4f5e1d5c83",
				"tarball": "https://registry.npmjs.org/postcss-stats/-/postcss-stats-1.0.0.tgz",
				"fileCount": 20,
				"unpackedSize": 116504,
				"npm-signature": "-----BEGIN PGP SIGNATURE-----\r\nVersion: OpenPGP.js v3.0.4\r\nComment: https://openpgpjs.org\r\n\r\nwsFcBAEBCAAQBQJb8583CRA9TVsSAnZWagAAwVYP/Arpei/dIqhFNTWSo9iS\nR+1r05tJjcS8QrZryWq1ssFDblxz7zDL4ZT5PX0nOAEHcPeQGotcyeyS+bOC\nbbFXziYf/UJvHrpOvpN+tdGLR/RZMIJX8g5vjNo0vYFUq0MnBN/zoB99SJr5\nWu0fVISdpEqSSt5IjI2Qk08rX6r4D/yTXIy5/7Ab1Pg2QWO0dgbrz7a++Fui\n1apADZuonneXmYr4lEkrApMfkjGlq39ooYAw8F8mai0MQu6Nug4dOoWm+8mP\nULZ0tXQbC/VCSYQToFqgnOrSAF4FMDUuBf3fxPlHBZ0onUzQE6O8o6D2/91p\nt3k3HUZQUFp1aAlFRytoVbQF+HxTB0u9LqHFDbm21Cw4UaCzdsoMKEuaT/Qm\nQFsFANw4l6VVLXSLIJafSRgcyO+p1FzeIxsAIDWcDcoPiKAF8lvf4gxs91A0\nuW8i4OnkC4IIrCxy2+NbDjRhnrCuiJ4ngfE13n1gL7CVXEVw3yDE0W/Z9eNC\nyQDld5HPRFAP/0vHa081jezBy30dnXJgWoPiFXUOOtBAFutl6UY0y8Ru4Ubj\nkb9rgrXONLyJjhu2gM3/7eKDYlINV85PggiTXfOPEhR9bHOn2F6vof9nrdpc\nsXDACgVHRMuFhIfPani+qliqroqNYNFcT5t6PChNCzkNgAQr+GpIGfcMpWAr\nWp15\r\n=hl4k\r\n-----END PGP SIGNATURE-----\r\n",
				"signatures": [
					{
						"keyid": "SHA256:jl3bwswu80PjjokCgh0o2w5c2U4LhQAE57gj9cz1kzA",
						"sig": "MEQCIHZxyHbZDuBGjwCtfBXmEc31CXntmnkgjA6qfDVN1LETAiAFB2zjBClM5sVI8uvFICV9p/Hu0sf3NuDnlV5oR7/V0g=="
					}
				]
			},
			"maintainers": [
				{
					"name": "karolis.sarapnickis",
					"email": "pastas.k@gmail.com"
				}
			],
			"directories": {},
			"_npmOperationalInternal": {
				"host": "s3://npm-registry-packages",
				"tmp": "tmp/postcss-stats_1.0.0_1542692662531_0.790943918252863"
			},
			"_hasShrinkwrap": false,
			"deprecated": "broken (empty) build"
		},
		"1.0.1": {
			"name": "postcss-stats",
			"version": "1.0.1",
			"description": "A PostCSS plugin to display stats",
			"keywords": [
				"css",
				"cssstats",
				"postcss",
				"postcss-plugin",
				"stats"
			],
			"homepage": "https://github.com/buz-zard/postcss-stats#readme",
			"bugs": {
				"url": "https://github.com/buz-zard/postcss-stats/issues"
			},
			"repository": {
				"type": "git",
				"url": "git+https://github.com/buz-zard/postcss-stats.git"
			},
			"license": "MIT",
			"author": {
				"name": "Karolis Šarapnickis"
			},
			"main": "lib/index.js",
			"scripts": {
				"build": "babel src --out-dir lib --source-maps",
				"clean": "rimraf lib",
				"develop": "npm run build -- --watch",
				"format": "prettier --write '**/*.*' && sort-package-json",
				"lint": "run-p lint:*",
				"lint:js": "eslint .",
				"lint:md": "markdownlint *.md -i node_modules",
				"qa": "run-p lint test",
				"semantic-release": "semantic-release",
				"test": "jest",
				"travis-deploy-once": "travis-deploy-once",
				"upgrade-interactive": "npm-check --update"
			},
			"husky": {
				"hooks": {
					"pre-commit": "lint-staged",
					"pre-push": "npm run qa"
				}
			},
			"config": {
				"commitizen": {
					"path": "cz-conventional-changelog"
				}
			},
			"jest": {
				"testRegex": "src/.+\\.test\\.js$"
			},
			"dependencies": {
				"brotli-size": "0.0.3",
				"chalk": "^2.4.1",
				"cli-table": "^0.3.1",
				"cssstats": "^3.2.0",
				"gzip-size": "^5.0.0",
				"pretty-bytes": "^5.1.0"
			},
			"devDependencies": {
				"@babel/cli": "^7.1.5",
				"@babel/core": "^7.1.5",
				"@babel/preset-env": "^7.1.5",
				"@k.sh/eslint-config": "^1.5.0",
				"babel-core": "^7.0.0-bridge.0",
				"babel-eslint": "^10.0.1",
				"babel-jest": "^23.6.0",
				"cz-conventional-changelog": "^2.1.0",
				"husky": "^1.1.3",
				"jest": "^23.6.0",
				"lint-staged": "^8.0.4",
				"markdownlint-cli": "^0.13.0",
				"npm-check": "^5.9.0",
				"npm-run-all": "^4.1.3",
				"postcss": "^7.0.6",
				"postcss-replace": "^1.0.3",
				"pretty-quick": "^1.8.0",
				"rimraf": "^2.6.2",
				"semantic-release": "^15.12.0",
				"sort-package-json": "^1.16.0",
				"travis-deploy-once": "^5.0.9"
			},
			"peerDependencies": {
				"postcss": ">= 7.0.0"
			},
			"lint-staged": {
				"package.json": [
					"sort-package-json",
					"git add"
				],
				"*.js": [
					"eslint --fix",
					"git add"
				],
				"*.{md,json}": [
					"pretty-quick --staged"
				]
			},
			"gitHead": "3e439f373b311096af6ab791de86a98ad7bb2f9b",
			"_id": "postcss-stats@1.0.1",
			"_npmVersion": "6.4.1",
			"_nodeVersion": "10.13.0",
			"_npmUser": {
				"name": "karolis.sarapnickis",
				"email": "pastas.k@gmail.com"
			},
			"dist": {
				"integrity": "sha512-UujAfcQk+0yIQnYpp2fGI1Q1OgA3nhEtwx7eST+Spv1/HK4Tr2mCNpKm90bMSKMrIPqvEWAHpl8lniGDYZNHyA==",
				"shasum": "d3a7ccae1254bba3a51c932f092eab6edf773f5c",
				"tarball": "https://registry.npmjs.org/postcss-stats/-/postcss-stats-1.0.1.tgz",
				"fileCount": 17,
				"unpackedSize": 26454,
				"npm-signature": "-----BEGIN PGP SIGNATURE-----\r\nVersion: OpenPGP.js v3.0.4\r\nComment: https://openpgpjs.org\r\n\r\nwsFcBAEBCAAQBQJb/RlJCRA9TVsSAnZWagAAKSkQAJHz3e/NohNFW1PLJVw4\nBFbtXxS7O1HwzOOJjPrY+RjImr6S8T6RvO+NXr1AXz332ouyHq51fPjcNLaO\nKjZeqwb+Zr36ZEQLBwcvyEvLaxN6o2l2MUQ3H36fG41zTWPltq2CS00CBO/c\nj18zYQyy6FjRXx/O4ND9ecSwX9oxU/obRv+dt7N/R/BMaMIQgvzO+x7h4X5g\ncZ2CImODABdI1oHT4b2qucMW29Z656FBg0EoKUNOyehPq8I1sBkaM/XkEJqW\nvaxhkXB+6u87aaiZ/F6WKWTUSbc+BOCWHnfjd/t4u/jZVqpNHfnL0zQk4QXy\nnE330WjmahswkF6Mv0x+5wnpYaC1EeeoyNDI96ii39VuGcrwbG7UFG7iwmXI\nsCYD1Xu4LaJ3j8BgdoJ5yRzneDsOgv+WrtrrjhrB/jh3mTU5hTYxL6vbiq+f\n8lD/vLzFneMJ/gPX4j9oKm6NBKTK6F2JGu76IAB9QKlS8gm2wXRKQHbb/1w2\nlgNr2RQYPfdqYXZMwAoVtBU75rSoy6yNwydA07Ta3Fm/iGc4U/FnZgr594b5\n2+R4+ghq6m9QO1+6fE9fphxmS20IgfxNzMV62jpG8a29SYpYbIlZ4Yhh+BCC\nEI5VUR1rbqewDzdZtCtuNHBKNRxx07seEGbIlxUH+wj+cBKeRFJU/HAuyAiv\niCQJ\r\n=01Pz\r\n-----END PGP SIGNATURE-----\r\n",
				"signatures": [
					{
						"keyid": "SHA256:jl3bwswu80PjjokCgh0o2w5c2U4LhQAE57gj9cz1kzA",
						"sig": "MEQCIGvwS45la4UEqIEaz/eK+asJEoCl8l6q0QL8RuobXlLzAiAd/E8tfKOGw1ie+a5WFz4cclLUm0sFKNLwuf9vD0LZkw=="
					}
				]
			},
			"maintainers": [
				{
					"name": "karolis.sarapnickis",
					"email": "pastas.k@gmail.com"
				}
			],
			"directories": {},
			"_npmOperationalInternal": {
				"host": "s3://npm-registry-packages",
				"tmp": "tmp/postcss-stats_1.0.1_1543313737151_0.15736913280355957"
			},
			"_hasShrinkwrap": false
		},
		"1.0.2": {
			"name": "postcss-stats",
			"version": "1.0.2",
			"description": "A PostCSS plugin to display stats",
			"keywords": [
				"css",
				"cssstats",
				"postcss",
				"postcss-plugin",
				"stats"
			],
			"homepage": "https://github.com/buz-zard/postcss-stats#readme",
			"bugs": {
				"url": "https://github.com/buz-zard/postcss-stats/issues"
			},
			"repository": {
				"type": "git",
				"url": "git+https://github.com/buz-zard/postcss-stats.git"
			},
			"license": "MIT",
			"author": {
				"name": "Karolis Šarapnickis"
			},
			"main": "lib/index.js",
			"scripts": {
				"build": "babel src --out-dir lib --source-maps",
				"clean": "rimraf lib",
				"develop": "npm run build -- --watch",
				"format": "prettier --write '**/*.*' && sort-package-json",
				"lint": "run-p lint:*",
				"lint:js": "eslint .",
				"lint:md": "markdownlint *.md -i node_modules",
				"qa": "run-p lint test",
				"semantic-release": "semantic-release",
				"test": "jest",
				"travis-deploy-once": "travis-deploy-once",
				"upgrade-interactive": "npm-check --update"
			},
			"husky": {
				"hooks": {
					"pre-commit": "lint-staged",
					"pre-push": "npm run qa"
				}
			},
			"config": {
				"commitizen": {
					"path": "cz-conventional-changelog"
				}
			},
			"jest": {
				"testRegex": "src/.+\\.test\\.js$"
			},
			"dependencies": {
				"brotli-size": "0.0.3",
				"chalk": "^2.4.1",
				"cli-table": "^0.3.1",
				"cssstats": "^3.2.0",
				"gzip-size": "^5.0.0",
				"pretty-bytes": "^5.1.0"
			},
			"devDependencies": {
				"@babel/cli": "^7.1.5",
				"@babel/core": "^7.1.5",
				"@babel/preset-env": "^7.1.5",
				"@k.sh/eslint-config": "^1.5.0",
				"babel-core": "^7.0.0-bridge.0",
				"babel-eslint": "^10.0.1",
				"babel-jest": "^23.6.0",
				"babel-plugin-add-module-exports": "^1.0.0",
				"cz-conventional-changelog": "^2.1.0",
				"husky": "^1.1.3",
				"jest": "^23.6.0",
				"lint-staged": "^8.0.4",
				"markdownlint-cli": "^0.13.0",
				"npm-check": "^5.9.0",
				"npm-run-all": "^4.1.3",
				"postcss": "^7.0.6",
				"postcss-replace": "^1.0.3",
				"pretty-quick": "^1.8.0",
				"rimraf": "^2.6.2",
				"semantic-release": "^15.12.0",
				"sort-package-json": "^1.16.0",
				"travis-deploy-once": "^5.0.9"
			},
			"peerDependencies": {
				"postcss": ">= 7.0.0"
			},
			"lint-staged": {
				"package.json": [
					"sort-package-json",
					"git add"
				],
				"*.js": [
					"eslint --fix",
					"git add"
				],
				"*.{md,json,babelrc}": [
					"pretty-quick --staged"
				]
			},
			"gitHead": "34093e69bf9a3d0eb2f833f09decfd09fdd536e3",
			"_id": "postcss-stats@1.0.2",
			"_npmVersion": "6.4.1",
			"_nodeVersion": "10.14.0",
			"_npmUser": {
				"name": "karolis.sarapnickis",
				"email": "pastas.k@gmail.com"
			},
			"dist": {
				"integrity": "sha512-0NGrJ6EtpVGrtVgwbaZxFyNSgjsqLS75hmDYG9LTBMSJZgWrTf0PDsOFPo9OELbFdzBXWf49g+A80xVG5qCKvQ==",
				"shasum": "4d44e47207b319ae66bb6caa015f72a4404e9a6d",
				"tarball": "https://registry.npmjs.org/postcss-stats/-/postcss-stats-1.0.2.tgz",
				"fileCount": 17,
				"unpackedSize": 26815,
				"npm-signature": "-----BEGIN PGP SIGNATURE-----\r\nVersion: OpenPGP.js v3.0.4\r\nComment: https://openpgpjs.org\r\n\r\nwsFcBAEBCAAQBQJb/m61CRA9TVsSAnZWagAAEpEP/iLCuiFUO89vqxYNTRYe\ngKOXbCafAQ6KMOX+cyqZVGkCfBeN7bNcyj95qn9StgayaNeynKO/yQzTdxo3\njbnV5Zt443yZ7/xSBkD/uFlEHrZC6dnq+uQ2C1XBfRxJ3n9luBLDsoQ4AnSF\nBKMQctjR3IAot1UxC3RePnDP5XugRmzfhFsL8da2DEJJ5phNBu85xBKG1cRc\nzCvz3PnKXzOEgTvzTBIO8wrB82yAcGZQZqBZCpRmWL//Bhp/XyuBr1Hih5Eb\n+fzesSGdGQjiElfeAWR1cfh0pgdCpBc40WTOVF3EfBQqGcKzLOtzeCzMGbMh\nSCdAJ8GYUr2KmF0pu8BcVrv0tkX6CspmD+33vtPuBkM840DAqky6Ui7kTXa3\n8ySGqFow4wktLzG1fxFQ1ecmKIZJbhLGj0Xtgh//+yb95gS4YujoSkbhStXX\nBH95cg9YZ+ReNUd1SnGQxE6fqHJ12dQe5z/qwe7B7OB2HICsSeSbR3R98kXt\nTKVpo6UVHP7L4PTa6sCEu6vVYWogeUD26StalV6HgEwSvQVqTDKNZCRU1wvS\n5fLSZwPYucFJjUI16vZ10JUyMggaWWEU1EKUA96tuNbyQe4SJBFt4u7Tgr/g\n38u2mVBX1qo86zPKkNf7CggAOPkJAURsjzcDeJnN3RK9iefvXcC0SDn7m3k+\nqGuh\r\n=pkQB\r\n-----END PGP SIGNATURE-----\r\n",
				"signatures": [
					{
						"keyid": "SHA256:jl3bwswu80PjjokCgh0o2w5c2U4LhQAE57gj9cz1kzA",
						"sig": "MEQCIEPB3Hs90SuMA1//lmVzs/rGVmxo9WDPyJ0+1JRqBCzjAiAWuWS+jz6RHrg7skhXt99MVLu4tpkpAFuxpvbDgqopNw=="
					}
				]
			},
			"maintainers": [
				{
					"name": "karolis.sarapnickis",
					"email": "pastas.k@gmail.com"
				}
			],
			"directories": {},
			"_npmOperationalInternal": {
				"host": "s3://npm-registry-packages",
				"tmp": "tmp/postcss-stats_1.0.2_1543401141046_0.20791867457840008"
			},
			"_hasShrinkwrap": false
		},
		"1.0.3": {
			"name": "postcss-stats",
			"version": "1.0.3",
			"description": "A PostCSS plugin to display stats",
			"keywords": [
				"css",
				"cssstats",
				"postcss",
				"postcss-plugin",
				"stats"
			],
			"homepage": "https://github.com/buz-zard/postcss-stats#readme",
			"bugs": {
				"url": "https://github.com/buz-zard/postcss-stats/issues"
			},
			"repository": {
				"type": "git",
				"url": "git+https://github.com/buz-zard/postcss-stats.git"
			},
			"license": "MIT",
			"author": {
				"name": "Karolis Šarapnickis"
			},
			"main": "lib/index.js",
			"scripts": {
				"build": "babel src --out-dir lib --source-maps",
				"clean": "rimraf lib",
				"develop": "npm run build -- --watch",
				"format": "prettier --write '**/*.*' && sort-package-json",
				"lint": "run-p lint:*",
				"lint:js": "eslint .",
				"lint:md": "markdownlint *.md -i node_modules",
				"qa": "run-p lint test",
				"semantic-release": "semantic-release",
				"test": "jest",
				"travis-deploy-once": "travis-deploy-once",
				"upgrade-interactive": "npm-check --update"
			},
			"husky": {
				"hooks": {
					"pre-commit": "lint-staged",
					"pre-push": "npm run qa"
				}
			},
			"config": {
				"commitizen": {
					"path": "cz-conventional-changelog"
				}
			},
			"jest": {
				"testRegex": "src/.+\\.test\\.js$"
			},
			"dependencies": {
				"brotli-size": "0.0.3",
				"chalk": "^2.4.1",
				"cli-table": "^0.3.1",
				"cssstats": "^3.2.0",
				"gzip-size": "^5.0.0",
				"pretty-bytes": "^5.1.0"
			},
			"devDependencies": {
				"@babel/cli": "^7.1.5",
				"@babel/core": "^7.1.5",
				"@babel/preset-env": "^7.1.5",
				"@k.sh/eslint-config": "^1.5.0",
				"babel-core": "^7.0.0-bridge.0",
				"babel-eslint": "^10.0.1",
				"babel-jest": "^23.6.0",
				"babel-plugin-add-module-exports": "^1.0.0",
				"cz-conventional-changelog": "^2.1.0",
				"husky": "^1.2.0",
				"jest": "^23.6.0",
				"lint-staged": "^8.1.0",
				"markdownlint-cli": "^0.13.0",
				"npm-check": "^5.9.0",
				"npm-run-all": "^4.1.5",
				"postcss": "^7.0.6",
				"postcss-replace": "^1.0.3",
				"pretty-quick": "^1.8.0",
				"rimraf": "^2.6.2",
				"semantic-release": "^15.12.5",
				"sort-package-json": "^1.17.0",
				"travis-deploy-once": "^5.0.9"
			},
			"peerDependencies": {
				"postcss": "^7"
			},
			"lint-staged": {
				"package.json": [
					"sort-package-json",
					"git add"
				],
				"*.js": [
					"eslint --fix",
					"git add"
				],
				"*.{md,json,babelrc}": [
					"pretty-quick --staged"
				]
			},
			"gitHead": "f95a6b04f1b421b652f1e55945dd0dd060f65d47",
			"_id": "postcss-stats@1.0.3",
			"_npmVersion": "6.5.0",
			"_nodeVersion": "10.15.0",
			"_npmUser": {
				"name": "karolis.sarapnickis",
				"email": "pastas.k@gmail.com"
			},
			"dist": {
				"integrity": "sha512-oFrbZ0u7cKVPpv6jr9xWWFD8rDGck6Wb/k96nyaXwe1rc/0y3nCtJFxm2NlzdFUMU6qePrmjmOr7fb/iXW9bJQ==",
				"shasum": "559ce79a6347cd7c4f608fdf34cde092b0e437af",
				"tarball": "https://registry.npmjs.org/postcss-stats/-/postcss-stats-1.0.3.tgz",
				"fileCount": 17,
				"unpackedSize": 26809,
				"npm-signature": "-----BEGIN PGP SIGNATURE-----\r\nVersion: OpenPGP.js v3.0.4\r\nComment: https://openpgpjs.org\r\n\r\nwsFcBAEBCAAQBQJcNfpnCRA9TVsSAnZWagAA3dMP/iBoiAATUbugL+mGesIE\nT2PSjuq4t8c6nOJY5cnjJdRFCtPF3jbpT9UIebN2qf1U64Zifi+ugwPHpj+x\nRaLS5JFcEhSASm49CtlzPmJDCm9KNoY87fW0mM15+kJnJ/nplGPtXXMdzyCB\nwsrT1dU+8T5lMI6GHcaAxZMPUcmblzo0hKvk/XCCo0dOVQ2BkMGmiw2/oijm\nimlnj21kxqigzudCRJr0H9taW0iVLOdcEHtr55Nsx4DHFNycpglrvWMQhIid\nQ9nOuDXa+lChuQ9xxRmOBzyQGTcyIiyf4Ldej9ZvwoTp9BTXsFirwJEhbkQD\nkqWpsY1wQvE5U/1LOeY3CWf3lcCE+ylcVf2wgLX/7B+fPCFhGPOjSzdmDaLg\ncm9yfR5PI3jJEuaWKV/ymqErQimqwSDy9/Dv5q0H9sQai8RY3LLCkI9roPvF\nQ8KpD85EHtHHLmgTTyQG9Y6pjDrQECxaxcYbVx/xML2xztfjFv+q+I0DMe0H\nIarNUr+JGEAjcWzFya46zd1JZtS5oQcsgJIu10BifnCX3/pxf4SI9a0QoY8M\nkbAQhW1v4rIZlW+yygf2dBqJgMu9qbgMkNkTtKB3Rhi91HFekqr1VXNfF7dh\n9RFVYNLwOcvSjQV9JAfggfpMkIojxQ5uSBLxMsv5rYqxSLtw0p41LSxNM3VX\nr9Ie\r\n=YeGV\r\n-----END PGP SIGNATURE-----\r\n",
				"signatures": [
					{
						"keyid": "SHA256:jl3bwswu80PjjokCgh0o2w5c2U4LhQAE57gj9cz1kzA",
						"sig": "MEYCIQCfe7koadnQUQRuFS4zZognArcFRKcFZWe8f8DWOu7VJwIhAJxkpXSCb9sF8E5GYn8o4U8eUNxGh9oTddr9OpHFuaLz"
					}
				]
			},
			"maintainers": [
				{
					"name": "karolis.sarapnickis",
					"email": "pastas.k@gmail.com"
				}
			],
			"directories": {},
			"_npmOperationalInternal": {
				"host": "s3://npm-registry-packages",
				"tmp": "tmp/postcss-stats_1.0.3_1547041382602_0.40773240509675857"
			},
			"_hasShrinkwrap": false
		},
		"1.0.4": {
			"name": "postcss-stats",
			"version": "1.0.4",
			"description": "A PostCSS plugin to display stats",
			"keywords": [
				"css",
				"cssstats",
				"postcss",
				"postcss-plugin",
				"stats"
			],
			"homepage": "https://github.com/buz-zard/postcss-stats#readme",
			"bugs": {
				"url": "https://github.com/buz-zard/postcss-stats/issues"
			},
			"repository": {
				"type": "git",
				"url": "git+https://github.com/buz-zard/postcss-stats.git"
			},
			"license": "MIT",
			"author": {
				"name": "Karolis Šarapnickis"
			},
			"main": "lib/index.js",
			"scripts": {
				"build": "babel src --out-dir lib --source-maps",
				"clean": "rimraf lib",
				"develop": "npm run build -- --watch",
				"format": "prettier --write '**/*.*' && sort-package-json",
				"lint": "run-p lint:*",
				"lint:js": "eslint .",
				"lint:md": "markdownlint *.md -i node_modules",
				"qa": "run-p lint test",
				"semantic-release": "semantic-release",
				"test": "jest",
				"travis-deploy-once": "travis-deploy-once",
				"upgrade-interactive": "npm-check --update"
			},
			"husky": {
				"hooks": {
					"pre-commit": "lint-staged",
					"pre-push": "npm run qa"
				}
			},
			"config": {
				"commitizen": {
					"path": "cz-conventional-changelog"
				}
			},
			"jest": {
				"testRegex": "src/.+\\.test\\.js$"
			},
			"dependencies": {
				"brotli-size": "0.0.3",
				"chalk": "^2.4.1",
				"cli-table": "^0.3.1",
				"cssstats": "^3.2.0",
				"gzip-size": "^5.0.0",
				"postcss": "^7.0.0",
				"pretty-bytes": "^5.1.0"
			},
			"devDependencies": {
				"@babel/cli": "^7.1.5",
				"@babel/core": "^7.1.5",
				"@babel/preset-env": "^7.1.5",
				"@k.sh/eslint-config": "^1.5.0",
				"babel-core": "^7.0.0-bridge.0",
				"babel-eslint": "^10.0.1",
				"babel-jest": "^23.6.0",
				"babel-plugin-add-module-exports": "^1.0.0",
				"cz-conventional-changelog": "^2.1.0",
				"husky": "^1.2.0",
				"jest": "^23.6.0",
				"lint-staged": "^8.1.0",
				"markdownlint-cli": "^0.13.0",
				"npm-check": "^5.9.0",
				"npm-run-all": "^4.1.5",
				"postcss-replace": "^1.0.3",
				"pretty-quick": "^1.8.0",
				"rimraf": "^2.6.2",
				"semantic-release": "^15.12.5",
				"sort-package-json": "^1.17.0",
				"travis-deploy-once": "^5.0.9"
			},
			"lint-staged": {
				"package.json": [
					"sort-package-json",
					"git add"
				],
				"*.js": [
					"eslint --fix",
					"git add"
				],
				"*.{md,json,babelrc}": [
					"pretty-quick --staged"
				]
			},
			"gitHead": "7b02bcff4dace721d33f1a2ef975d8691bcabc3b",
			"_id": "postcss-stats@1.0.4",
			"_npmVersion": "6.5.0",
			"_nodeVersion": "10.15.0",
			"_npmUser": {
				"name": "karolis.sarapnickis",
				"email": "pastas.k@gmail.com"
			},
			"dist": {
				"integrity": "sha512-GuVlacc+xQWDgs95odjk6aknI1pHvBS2WjsIOc0X2K8SAljY2MuLO0QgCTzuIB91BF9tege+q7wPVRvAs0/4HQ==",
				"shasum": "5d2a0b83d71b49679c744f84869038042b29b330",
				"tarball": "https://registry.npmjs.org/postcss-stats/-/postcss-stats-1.0.4.tgz",
				"fileCount": 17,
				"unpackedSize": 26760,
				"npm-signature": "-----BEGIN PGP SIGNATURE-----\r\nVersion: OpenPGP.js v3.0.4\r\nComment: https://openpgpjs.org\r\n\r\nwsFcBAEBCAAQBQJcNwcTCRA9TVsSAnZWagAAYu4QAIRIvT+AQcr+IPFiuGU0\n5eBjVR4K63t/TQjGqrzFZe6UejvZ6Um+u08le1JxCLbgGsDAnJZXAwFBj88t\nKR0r9tLk+vWfVcCzZny6oVMsHgA5LY8iZVsxIS5FNVLCqjmuiflnnJf19iv1\n8oriRgfyX0yKPIsPbY7gFUmkkT1YJg065trrLfwIH92JIaKy0FMYhCtQvUeb\nDqAlhjTWo1SybmNS6iplb4vU2QMMqgEyW/NiWJlYGvf7aYKtrs7whiyT7L2l\n+oaNIAVAtGSuMr1pGR+TK31gGgSzxoyAXH3Kdg+rfg4sfDN+84G3j2pBMtiu\nBuahRwijm1biJF42BFx+9Z3R4GzXJBuUozBudkoGrLX9oJmcVaaJTBRHeuHR\naoKlHLhhzQhpjOYOSfDAbY21Yg/lTUHXui4A+YO/kkmY93V42xLtW/Yd0o70\nbrwfMHA2YXcHDK3ME2XRcsb6aEBpWJdD052YAYNrFt2PCLlHpb51PSjLSHge\n7AAP9DHjiLKMPw4cQNywAz05xy76jtJJ2jTaYNrFAGVl71iXzk/JIsmCh7Am\nVVJnmlEPKqu1cYmQmGdxEEAq/QWoipEA/3lmyOqEi7NxcW7ae7JLS26PTZtM\nyIhepAYHvqX+KcCOJ1I5C2ZZU1gtIyn2otQdUv8UjBrj12VqD1Ue45tKZcOM\nF7jQ\r\n=Es0S\r\n-----END PGP SIGNATURE-----\r\n",
				"signatures": [
					{
						"keyid": "SHA256:jl3bwswu80PjjokCgh0o2w5c2U4LhQAE57gj9cz1kzA",
						"sig": "MEUCIG5F/QgY8EBGkqrgzInPGbGEViYTwWO3caPADExrGFGQAiEA+s7wUPqj+XQ1RH3VeZHvKRdb+29CksWFO2Lj15egzto="
					}
				]
			},
			"maintainers": [
				{
					"name": "karolis.sarapnickis",
					"email": "pastas.k@gmail.com"
				}
			],
			"directories": {},
			"_npmOperationalInternal": {
				"host": "s3://npm-registry-packages",
				"tmp": "tmp/postcss-stats_1.0.4_1547110162636_0.40258246361134287"
			},
			"_hasShrinkwrap": false
		},
		"1.0.5": {
			"name": "postcss-stats",
			"version": "1.0.5",
			"description": "A PostCSS plugin to display stats",
			"keywords": [
				"css",
				"cssstats",
				"postcss",
				"postcss-plugin",
				"stats"
			],
			"homepage": "https://github.com/buz-zard/postcss-stats#readme",
			"bugs": {
				"url": "https://github.com/buz-zard/postcss-stats/issues"
			},
			"repository": {
				"type": "git",
				"url": "git+https://github.com/buz-zard/postcss-stats.git"
			},
			"license": "MIT",
			"author": {
				"name": "Karolis Šarapnickis"
			},
			"main": "lib/index.js",
			"scripts": {
				"build": "babel src --out-dir lib --source-maps",
				"clean": "rimraf lib",
				"develop": "npm run build -- --watch",
				"format": "prettier --write '**/*.*' && sort-package-json",
				"lint": "run-p lint:*",
				"lint:js": "eslint .",
				"lint:md": "markdownlint *.md -i node_modules",
				"qa": "run-p lint test",
				"semantic-release": "semantic-release",
				"test": "jest",
				"travis-deploy-once": "travis-deploy-once",
				"upgrade-interactive": "npm-check --update"
			},
			"husky": {
				"hooks": {
					"pre-commit": "lint-staged",
					"pre-push": "npm run qa"
				}
			},
			"config": {
				"commitizen": {
					"path": "cz-conventional-changelog"
				}
			},
			"jest": {
				"testRegex": "src/.+\\.test\\.js$"
			},
			"dependencies": {
				"brotli-size": "0.1.0",
				"chalk": "^2.4.1",
				"cli-table": "^0.3.1",
				"cssstats": "^3.2.0",
				"gzip-size": "^5.0.0",
				"postcss": "^7.0.0",
				"pretty-bytes": "^5.1.0"
			},
			"devDependencies": {
				"@babel/cli": "^7.1.5",
				"@babel/core": "^7.1.5",
				"@babel/preset-env": "^7.1.5",
				"@k.sh/eslint-config": "^1.5.0",
				"babel-core": "^7.0.0-bridge.0",
				"babel-eslint": "^10.0.1",
				"babel-jest": "^23.6.0",
				"babel-plugin-add-module-exports": "^1.0.0",
				"cz-conventional-changelog": "^2.1.0",
				"husky": "^2.0.0",
				"jest": "^23.6.0",
				"lint-staged": "^8.1.0",
				"markdownlint-cli": "^0.15.0",
				"npm-check": "^5.9.0",
				"npm-run-all": "^4.1.5",
				"postcss-replace": "^1.0.3",
				"pretty-quick": "^1.8.0",
				"rimraf": "^2.6.2",
				"semantic-release": "^15.12.5",
				"sort-package-json": "^1.17.0",
				"travis-deploy-once": "^5.0.9"
			},
			"lint-staged": {
				"package.json": [
					"sort-package-json",
					"git add"
				],
				"*.js": [
					"eslint --fix",
					"git add"
				],
				"*.{md,json,babelrc}": [
					"pretty-quick --staged"
				]
			},
			"gitHead": "29c209785640711eee9816962db1ea7592309736",
			"_id": "postcss-stats@1.0.5",
			"_npmVersion": "6.5.0",
			"_nodeVersion": "10.15.3",
			"_npmUser": {
				"name": "karolis.sarapnickis",
				"email": "pastas.k@gmail.com"
			},
			"dist": {
				"integrity": "sha512-MFj5pRNae9R6ZgNVPXu6NPyGSA24DojUcRok7LO7QnTBB5k2rt/xL0dQCePXQ4NnEkHrnIz8fjM5SaQfpZl8TQ==",
				"shasum": "8d201ce61b800c998d19dcc31f2a283e57b815c0",
				"tarball": "https://registry.npmjs.org/postcss-stats/-/postcss-stats-1.0.5.tgz",
				"fileCount": 17,
				"unpackedSize": 26760,
				"npm-signature": "-----BEGIN PGP SIGNATURE-----\r\nVersion: OpenPGP.js v3.0.4\r\nComment: https://openpgpjs.org\r\n\r\nwsFcBAEBCAAQBQJc0abwCRA9TVsSAnZWagAALrIQAJU/9dDssOB3ihZJqlXP\nJkte4kXHpZVjTWL/Yrearp9lTi6px2NckwnDH8QCFYk1LM6Ah7WWzUXpwZ4g\n3SClzwU9Q9Gw/3THJzW3z4Q4XUZTNnqzW5v9aKzpNx4woTW+BPMA4EYMsbHv\n8RE7cEJcR/syO7cvqtv4NFDDeVqzIs1kXGCyNjOutVOdsY/5H9PDONvXygjt\nPLEsIIUvc/NAdfpRh6FdrPp0zlYPrd+FOKhKCFQU3pTL3EkITJuTmW4mpCBD\nHCSokH7lBHwjeRggnpnhOA/H4kmMmHJWO0NqMUzyEZhfBJWQy3AMaDAQHPSP\nWJtgEuuJIRcY22Pt32uhf8bUxg9fk1qXGFpz665rkbtNLgwX5uBp6LAksYGg\nMnLqIMeUEAajAa5fxYC48d2X0HsaCl+Oj4cxOTJ3uoM6678bqC+xhXQGMDDi\nhMUwSsAAgwvCFyvb6iZQ61cMQBySkQ9y52H9bVECQcIFwWdpSrkE7Ml/t0ij\noCCF0dkGsmVeKfZLkU6tzkIKTZcxvwXC/oro7Lq5GvT3OqT51XHf3eXi4nDL\nItWdD6OR2f/vLb9U4Zow4X1IHTUTDzMe+FeLS4gNvae80exMhmNWnQoNBVr9\nzAI/VGX2gGUDrEqM2wKa9uoPXbCq5wsZcy61rtdX9CoASxuD1dpAPfRZ9r3i\nHsa+\r\n=aY10\r\n-----END PGP SIGNATURE-----\r\n",
				"signatures": [
					{
						"keyid": "SHA256:jl3bwswu80PjjokCgh0o2w5c2U4LhQAE57gj9cz1kzA",
						"sig": "MEUCIGmT3k993gNYkyPgznqndvqx0f+w4/qUy2j9JyAjGrOFAiEAhjB8qtCde4el17ewuCv1aQ6sez4NImQiaF+3zE5L7mE="
					}
				]
			},
			"maintainers": [
				{
					"name": "karolis.sarapnickis",
					"email": "pastas.k@gmail.com"
				}
			],
			"directories": {},
			"_npmOperationalInternal": {
				"host": "s3://npm-registry-packages",
				"tmp": "tmp/postcss-stats_1.0.5_1557243631176_0.6188943246910796"
			},
			"_hasShrinkwrap": false
		},
		"1.1.0": {
			"name": "postcss-stats",
			"version": "1.1.0",
			"description": "A PostCSS plugin to display stats",
			"keywords": [
				"css",
				"cssstats",
				"postcss",
				"postcss-plugin",
				"stats"
			],
			"homepage": "https://github.com/karolis-sh/postcss-stats#readme",
			"bugs": {
				"url": "https://github.com/karolis-sh/postcss-stats/issues"
			},
			"repository": {
				"type": "git",
				"url": "git+https://github.com/karolis-sh/postcss-stats.git"
			},
			"license": "MIT",
			"author": {
				"name": "Karolis Šarapnickis"
			},
			"main": "lib/index.js",
			"scripts": {
				"build": "babel src --out-dir lib --source-maps",
				"clean": "rimraf lib",
				"develop": "npm run build -- --watch",
				"format": "prettier --write '**/*.*' && sort-package-json",
				"lint": "run-p lint:*",
				"lint:js": "eslint .",
				"lint:md": "markdownlint *.md -i node_modules",
				"qa": "run-p lint test",
				"semantic-release": "semantic-release",
				"test": "jest",
				"travis-deploy-once": "travis-deploy-once",
				"upgrade-interactive": "npm-check --update"
			},
			"husky": {
				"hooks": {
					"pre-commit": "lint-staged",
					"pre-push": "npm run qa"
				}
			},
			"lint-staged": {
				"*.js": [
					"eslint --fix",
					"git add"
				],
				"*.{md,json}": [
					"pretty-quick --staged"
				],
				"package.json": [
					"sort-package-json",
					"git add"
				]
			},
			"config": {
				"commitizen": {
					"path": "cz-conventional-changelog"
				}
			},
			"jest": {
				"testRegex": "src/.+\\.test\\.js$"
			},
			"dependencies": {
				"brotli-size": "0.1.0",
				"chalk": "^2.4.1",
				"cli-table": "^0.3.1",
				"cssstats": "^3.4.0",
				"gzip-size": "^5.1.1",
				"postcss": "^7.0.18",
				"pretty-bytes": "^5.3.0"
			},
			"devDependencies": {
				"@babel/cli": "^7.6.0",
				"@babel/core": "^7.6.0",
				"@babel/preset-env": "^7.6.0",
				"@k.sh/eslint-config": "^1.13.0",
				"babel-core": "^7.0.0-bridge.0",
				"babel-eslint": "^10.0.3",
				"babel-jest": "^24.9.0",
				"babel-plugin-add-module-exports": "^1.0.2",
				"commitizen": "^4.0.3",
				"cssnano": "^4.1.10",
				"cz-conventional-changelog": "^3.0.2",
				"fs-extra": "^8.1.0",
				"husky": "^3.0.5",
				"jest": "^24.9.0",
				"lint-staged": "^9.2.5",
				"markdownlint-cli": "^0.18.0",
				"npm-check": "^5.9.0",
				"npm-run-all": "^4.1.5",
				"postcss-replace": "^1.0.7",
				"pretty-quick": "^1.11.1",
				"rimraf": "^3.0.0",
				"semantic-release": "^15.13.24",
				"sort-package-json": "^1.22.1",
				"travis-deploy-once": "^5.0.11"
			},
			"gitHead": "b2f050c6bd22427ad1e4520a6bd6226c63460d63",
			"_id": "postcss-stats@1.1.0",
			"_nodeVersion": "10.16.3",
			"_npmVersion": "6.11.3",
			"dist": {
				"integrity": "sha512-XYuoVuCMeP++fVtG/CY3c0ICZ3f9+Bj8ohFb1BTjEMCNCl7YYKl7pOnlWYpOYr5/izAs+u4UX1F/rTD2JP++xw==",
				"shasum": "19f0def1de396d04aa86b97a38a087ce592ead44",
				"tarball": "https://registry.npmjs.org/postcss-stats/-/postcss-stats-1.1.0.tgz",
				"fileCount": 17,
				"unpackedSize": 28129,
				"npm-signature": "-----BEGIN PGP SIGNATURE-----\r\nVersion: OpenPGP.js v3.0.4\r\nComment: https://openpgpjs.org\r\n\r\nwsFcBAEBCAAQBQJdeIpQCRA9TVsSAnZWagAADRUP/2P6riAYExjBSbl7S3uM\nq4KDXarEPWPee3KssmZzieHcdBoFbchWEqPOiUHPb7GX8YnqxMImQKn2JzWa\nGf1qAlM8yKJrya5DnA8p1+n2WqbEFKjsPC798K8QgXYOzUvHwTZkU4KLbLhh\ns+PpdkLSDOVs1ZoCBMXFRcQkdnq6s2iGJWXM9o9I8IjEpBgRL96Yv6bfON6U\nOXV28vgeUoad2zE/yXBJ2ANa3k0ZKBQosTg959xtKe8srIlpZ8nFAFJba88R\niKitrkyG+ZM4WdG6Y5pVmmMI4EKuQcnq+Bcz+c9K8TBBSK4CEBNCvEcMhRYU\nK9jNYEptny2eWWYwnaAowgmK3nlmRadqSz7H+rO82IAGNWq7QiQpPCXEZaYi\ncIBs6YNjU2vLfmwyo27Kv32aHEFatcT/Y6xlDFFvtfgSZBt36SXObAD1IZKw\nFlwnpkKdAZSDvwncCzd0Aa174Hv0S7zG1jVl7U6MLGaKhSth9ylGm3gStNX/\nLAmSYgEn0XuZeM47RXmWCpZYEoC4efUOi/R4wQmkOC6ChuHOpzZDOyn/TBsY\n1iRtQ8KwMFVDy+iRa3+C8XkAQk0clRY3HqAg7nZ4mNXKFgPDCk62E17hyesm\n1/F+IZmDF4rdc56kU+GhXA7LEJLPEoi/SPrXNQhovx9WHMQgS4d8HBmsSv4U\nzxvS\r\n=S/kX\r\n-----END PGP SIGNATURE-----\r\n",
				"signatures": [
					{
						"keyid": "SHA256:jl3bwswu80PjjokCgh0o2w5c2U4LhQAE57gj9cz1kzA",
						"sig": "MEQCIH+l/ZjKUYKPBylOE4IhpGt1y3izHqeTKhV29G4RXo8dAiBTFFJxCxLxINJWGrSb8EFNyT4nh62OG8VY/InKSl0leg=="
					}
				]
			},
			"maintainers": [
				{
					"name": "karolis.sarapnickis",
					"email": "pastas.k@gmail.com"
				}
			],
			"_npmUser": {
				"name": "karolis.sarapnickis",
				"email": "pastas.k@gmail.com"
			},
			"directories": {},
			"_npmOperationalInternal": {
				"host": "s3://npm-registry-packages",
				"tmp": "tmp/postcss-stats_1.1.0_1568180815899_0.4837633831015309"
			},
			"_hasShrinkwrap": false
		}
	},
	"time": {
		"created": "2018-11-12T05:24:34.918Z",
		"0.0.0": "2018-11-12T05:24:35.065Z",
		"modified": "2022-05-13T06:48:45.012Z",
		"1.0.0": "2018-11-20T05:44:22.684Z",
		"1.0.1": "2018-11-27T10:15:37.309Z",
		"1.0.2": "2018-11-28T10:32:21.173Z",
		"1.0.3": "2019-01-09T13:43:02.683Z",
		"1.0.4": "2019-01-10T08:49:22.737Z",
		"1.0.5": "2019-05-07T15:40:31.323Z",
		"1.1.0": "2019-09-11T05:46:56.045Z"
	},
	"maintainers": [
		{
			"name": "karolis.sarapnickis",
			"email": "pastas.k@gmail.com"
		}
	],
	"homepage": "https://github.com/karolis-sh/postcss-stats#readme",
	"keywords": [
		"css",
		"cssstats",
		"postcss",
		"postcss-plugin",
		"stats"
	],
	"repository": {
		"type": "git",
		"url": "git+https://github.com/karolis-sh/postcss-stats.git"
	},
	"author": {
		"name": "Karolis Šarapnickis"
	},
	"bugs": {
		"url": "https://github.com/karolis-sh/postcss-stats/issues"
	},
	"license": "MIT",
	"readme": "# postcss-stats\n\nA simple 1 dependency PostCSS plugin to print stats to the console.\n\nUses [cssstats] under the hood.\n\n[![npm version][version-badge]][version]\n[![Build Status][build-badge]][build]\n[![License: MIT][license-badge]][license]\n\n[![semantic-release][semantic-release-badge]][semantic-release]\n[![code style: prettier][code-style-badge]][code-style]\n\n## Installation\n\n> npm install postcss-stats\n\n## Usage\n\nJust add the `postcss-stats` plugin:\n\n```javascript\npostcss()\n  .use(postcssStats())\n  .process(css);\n```\n\nAnd it will output the stats table to the console:\n\n![sample output][sample-output]\n\n## References\n\n- <https://cssstats.com/>\n\n## License\n\nMIT\n\n[sample-output]: /docs/sample-output.png\n[cssstats]: https://github.com/cssstats/core\n[version-badge]: https://badge.fury.io/js/postcss-stats.svg\n[version]: https://www.npmjs.com/package/postcss-stats\n[build-badge]: https://travis-ci.org/karolis-sh/postcss-stats.svg?branch=master\n[build]: https://travis-ci.org/karolis-sh/postcss-stats\n[license-badge]: https://img.shields.io/badge/License-MIT-yellow.svg\n[license]: https://opensource.org/licenses/MIT\n[semantic-release-badge]: https://img.shields.io/badge/%20%20%F0%9F%93%A6%F0%9F%9A%80-semantic--release-e10079.svg\n[semantic-release]: https://github.com/semantic-release/semantic-release\n[code-style-badge]: https://img.shields.io/badge/code_style-prettier-ff69b4.svg\n[code-style]: https://github.com/prettier/prettier\n",
	"readmeFilename": "README.md",
	"description": "A PostCSS plugin to display stats",
	"_downloads": [
		9,
		9,
		18,
		31,
		21,
		20,
		20
	]
}